elkm1/__init__.py
elkm1/__version__.py
elkm1/areas.py
elkm1/const.py
elkm1/counters.py
elkm1/elements.py
elkm1/elk.py
elkm1/keypads.py
elkm1/lights.py
elkm1/message.py
elkm1/outputs.py
elkm1/panel.py
elkm1/proto.py
elkm1/settings.py
elkm1/tasks.py
elkm1/users.py
elkm1/util.py
elkm1/zones.py
elkm1-0.1.0.dist-info/METADATA
elkm1-0.1.0.dist-info/RECORD
elkm1-0.1.0.dist-info/WHEEL
elkm1-0.1.0.dist-info/top_level.txt
