Metadata-Version: 2.1
Name: elkm1
Version: 0.1.0
Summary: Library for interacting with ElkM1 alarm/automation panel.
Home-page: https://github.com/gwww/elkm1
Author: Glenn Waters
Author-email: gwwaters+elkm1@gmail.com
License: MIT
Platform: UNKNOWN
Classifier: Development Status :: 3 - Alpha
Classifier: Intended Audience :: Developers
Classifier: License :: OSI Approved :: MIT License
Classifier: Programming Language :: Python
Classifier: Programming Language :: Python :: 3.5
Classifier: Programming Language :: Python :: 3.6
Requires-Python: >=3.5
